.svn_ignore.txt
LICENSE
README.rst
setup.py
django_wikiapp.egg-info/PKG-INFO
django_wikiapp.egg-info/SOURCES.txt
django_wikiapp.egg-info/dependency_links.txt
django_wikiapp.egg-info/not-zip-safe
django_wikiapp.egg-info/top_level.txt
docs/api.txt
docs/dependencies.txt
docs/index.txt
docs/install.txt
wiki/__init__.py
wiki/admin.py
wiki/feeds.py
wiki/forms.py
wiki/management.py
wiki/models.py
wiki/static_urls.py
wiki/urls.py
wiki/utils.py
wiki/views.py
wiki/media/wikiapp.css
wiki/templates/feeds/history_description.html
wiki/templates/feeds/history_title.html
wiki/templates/notification/wiki_article_edited/full.txt
wiki/templates/notification/wiki_article_edited/notice.html
wiki/templates/notification/wiki_observed_article_changed/full.txt
wiki/templates/notification/wiki_observed_article_changed/notice.html
wiki/templates/notification/wiki_revision_reverted/full.txt
wiki/templates/notification/wiki_revision_reverted/notice.html
wiki/templates/wiki/article_content.html
wiki/templates/wiki/article_teaser.html
wiki/templates/wiki/base.html
wiki/templates/wiki/changeset.html
wiki/templates/wiki/edit.html
wiki/templates/wiki/history.html
wiki/templates/wiki/index.html
wiki/templates/wiki/messages.html
wiki/templates/wiki/recentchanges.html
wiki/templates/wiki/searchbox.html
wiki/templates/wiki/view.html
wiki/templates/wiki/wiki_title.html
wiki/templatetags/__init__.py
wiki/templatetags/creole.py
wiki/templatetags/restructuredtext.py
wiki/templatetags/switchcase.py
wiki/templatetags/wiki.py
wiki/templatetags/wikiurl.py